wtforms_dateutil/__init__.py
WTForms_dateutil-0.1.dist-info/LICENSE.md
WTForms_dateutil-0.1.dist-info/METADATA
WTForms_dateutil-0.1.dist-info/WHEEL
WTForms_dateutil-0.1.dist-info/top_level.txt
WTForms_dateutil-0.1.dist-info/RECORD
